rclckspace/RclckSpace.py
rclckspace/__init__.py
rclckspace-0.3.dist-info/METADATA
rclckspace-0.3.dist-info/WHEEL
rclckspace-0.3.dist-info/top_level.txt
rclckspace-0.3.dist-info/RECORD
