Metadata-Version: 2.4
Name: RclckSpace
Version: 0.3
Summary: API для сокращения ссылок через rclck.space
Home-page: https://github.com/your-repo/rclckspace
Author: RostorVLasov
Classifier: Programming Language :: Python :: 3
Classifier: License :: OSI Approved :: MIT License
Classifier: Operating System :: OS Independent
Requires-Dist: requests
Dynamic: author
Dynamic: classifier
Dynamic: home-page
Dynamic: requires-dist
Dynamic: summary
